{
  "/eus/.*": {
    "pg": "http://eus.egov:8080",
    "ke": "http://eus.egov:8080",
    "in": "http://eus.egov:8080"
  },
   "/egov-url-shortening/.*": {
    "pg": "http://egov-url-shortening.egov:8080",
    "ke": "http://egov-url-shortening.egov:8080",
    "in": "http://egov-url-shortening.egov:8080"
  },
  "/egov-idgen/.*": {
    "pg": "http://egov-idgen.egov:8080",
    "ke": "http://egov-idgen.egov:8080",
    "in": "http://egov-idgen.egov:8080"
  },
  "/egov-localization/.*": {
    "pg": "http://egov-localization.egov:8080",
    "ke": "http://egov-localization.egov:8080",
    "in": "http://egov-localization.egov:8080"
  },
  "/egov-mdms-service/.*": {
    "pg": "http://egov-mdms-service.egov:8080",
    "ke": "http://egov-mdms-service.egov:8080",
    "in": "http://egov-mdms-service:8080"
  },
  "/pt-calculator-v2/.*": {
    "pg": "http://pt-calculator-v2.staging:8080",
    "ke": "http://pt-calculator-v2.kenya:8080"
  },
  "/property-services/.*": {
    "ke": "http://property-services.egov:8080",
    "pg": "http://property-services.egov:8080"
  },
  "/billing-service/.*": {
    "ke": "http://billing-service.egov:8080",
    "pg": "http://billing-service.egov:8080"
  },
  "/tl-calculator/.*": {
    "pg": "http://tl-calculator.staging:8080",
    "ke": "http://tl-calculator.kenya:8080"
  },
  "/ws-calculator/.*": {
    "pg": "http://ws-calculator.staging:8080",
    "ke": "http://ws-calculator.kenya:8080"
  },
  "/sw-calculator/.*": {
    "pg": "http://sw-calculator.staging:8080",
    "ke": "http://sw-calculator.kenya:8080"
  },
  "/firenoc-calculator/.*": {
    "pg": "http://firenoc-calculator.staging:8080",
    "ke": "http://firenoc-calculator.kenya:8080"
  },
  "/pg-service/.*": {
    "pg": "http://egov-pg-service.egov:8080",
    "ke": "http://egov-pg-service.egov:8080"
  },
  "/dashboard-analytics/.*": {
    "pg": "http://dashboard-analytics.staging:8080",
    "ke": "http://dashboard-analytics.kenya:8080"
  },
  "/report/.*": {
    "pg": "http://report.egov:8080",
    "ke": "http://report.egov:8080"
  },
  "/pdf-service/.*": {
    "pg": "http://pdf-service.staging:8080",
    "ke": "http://pdf-service.kenya:8080"
  },
  "/filestore/.*": {
    "pg": "http://egov-filestore.egov:8080",
    "ke": "http://egov-filestore.egov:8080",
    "in": "http://egov-filestore.egov:8080"
  },
  "/echallan-calculator/.*": {
    "pg": "http://echallan-calculator.staging:8080",
    "ke": "http://echallan-calculator.kenya:8080"
  },
  "/edcr/.*": {
    "pg": "http://egov-edcr.staging:8080",
    "ke": "http://egov-edcr.kenya:8080"
  },
    "/egov-user/.*": {
    "pg": "http://egov-user.egov:8080",
    "ke": "http://egov-user.egov:8080",
    "in": "http://egov-user.egov:8080"
  },
  "/egov-pdf/.*": {
    "pg": "http://egov-pdf.egov:8080",
    "ke": "http://egov-pdf.egov:8080"
  },
  "/inbox/.*": {
    "pg": "http://inbox.staging:8080",
    "ke": "http://inbox.kenya:8080"
  },
   "/egov-searcher/.*": {
    "pg": "http://egov-searcher.egov:8080",
    "ke": "http://egov-searcher.egov:8080"
  },
  "/bpa-calculator/.*": {
    "pg": "http://bpa-calculator.staging:8080",
    "ke": "http://bpa-calculator.kenya:8080"
  }
}
